qir.py
qir-0.1.1.dist-info/LICENSE.txt
qir-0.1.1.dist-info/METADATA
qir-0.1.1.dist-info/WHEEL
qir-0.1.1.dist-info/top_level.txt
qir-0.1.1.dist-info/RECORD
