Metadata-Version: 2.1
Name: qir
Version: 0.1.1
Summary: Quantum Impurity Relaxometry (QIR) is a package for QI relaxation rates calculations.
Home-page: https://github.com/helenala/qi-relaxometry
Author: Helena La
Author-email: heelenala@gmail.com
License: UNKNOWN
Platform: UNKNOWN
Classifier: Programming Language :: Python :: 3.9
Classifier: License :: OSI Approved :: GNU General Public License v2 or later (GPLv2+)
Classifier: Operating System :: OS Independent
License-File: LICENSE.txt
Requires-Dist: matplotlib (~=3.5.2)
Requires-Dist: numpy (~=1.22.3)
